README.txt
setup.py
collective/__init__.py
collective.psc.blobstorage.egg-info/PKG-INFO
collective.psc.blobstorage.egg-info/SOURCES.txt
collective.psc.blobstorage.egg-info/dependency_links.txt
collective.psc.blobstorage.egg-info/entry_points.txt
collective.psc.blobstorage.egg-info/namespace_packages.txt
collective.psc.blobstorage.egg-info/not-zip-safe
collective.psc.blobstorage.egg-info/requires.txt
collective.psc.blobstorage.egg-info/top_level.txt
collective/psc/__init__.py
collective/psc/blobstorage/__init__.py
collective/psc/blobstorage/adapters.py
collective/psc/blobstorage/configure.zcml
collective/psc/blobstorage/profiles.zcml
collective/psc/blobstorage/profiles/default/metadata.xml
collective/psc/blobstorage/tests/__init__.py
collective/psc/blobstorage/tests/test_basic.py
collective/psc/blobstorage/tests/test_blobstorage.py
collective/psc/blobstorage/tests/test_content.py
docs/CHANGES.txt
docs/CONTRIBUTORS.txt