Metadata-Version: 1.0
Name: collective.psc.blobstorage
Version: 0.1.1
Summary: Blob storage for PloneSoftwareCenter
Home-page: http://svn.plone.org/svn/collective/collective.psc.blobstorage
Author: Tarek Ziade
Author-email: tarek@ziade.org
License: GPL
Keywords: psc disutils storage
Platform: UNKNOWN
Classifier: Programming Language :: Python
Classifier: Topic :: Software Development :: Libraries :: Python Modules
